setup.py
labelprop/__init__.py
labelprop.egg-info/PKG-INFO
labelprop.egg-info/SOURCES.txt
labelprop.egg-info/dependency_links.txt
labelprop.egg-info/top_level.txt