Metadata-Version: 1.1
Name: labelprop
Version: 0.1.3
Summary: Python implementation of label propagation
Home-page: https://github.com/ZwEin27/python-labelpropagation
Author: Lingzhe Teng
Author-email: zwein27@gmail.com
License: UNKNOWN
Download-URL: https://github.com/ZwEin27/python-labelpropagation/tarball/0.1.3
Keywords: label propagation,label,propagation,labelpropagation
Platform: UNKNOWN
